udpy/__init__.py
udpy/base.py
udpy-1.0.0.dist-info/LICENSE
udpy-1.0.0.dist-info/LICENSE-OLD
udpy-1.0.0.dist-info/WHEEL
udpy-1.0.0.dist-info/METADATA
udpy-1.0.0.dist-info/RECORD
