Metadata-Version: 2.1
Name: udpy
Version: 1.0.0
Summary: Urban dictionary API wrapper for Python
License: MIT
Author: prostomarkeloff
Requires-Python: >=3.6,<4.0
Classifier: License :: OSI Approved :: MIT License
Classifier: Programming Language :: Python :: 3
Classifier: Programming Language :: Python :: 3.6
Classifier: Programming Language :: Python :: 3.7
Classifier: Programming Language :: Python :: 3.8
Requires-Dist: requests (>=2.23.0,<3.0.0)
